anthos.py
anthos-1.0.4.dist-info/licenses/LICENSE
anthos-1.0.4.dist-info/METADATA
anthos-1.0.4.dist-info/WHEEL
anthos-1.0.4.dist-info/top_level.txt
anthos-1.0.4.dist-info/RECORD
