Metadata-Version: 2.4
Name: anthos
Version: 1.0.4
Summary: Make waveform widgets beautifully.
License-File: LICENSE
Requires-Dist: readme-md>=2018.11.23
Dynamic: license-file
